{
    "key": "group_6160f7d046e91",
    "title": "Block : Media Content Post",
    "fields": [
        {
            "key": "field_6160f7d6985cd",
            "label": "Post",
            "name": "post",
            "type": "relationship",
            "instructions": "",
            "required": 0,
            "conditional_logic": 0,
            "wrapper": {
                "width": "",
                "class": "",
                "id": ""
            },
            "post_type": [
                "post"
            ],
            "taxonomy": "",
            "filters": [
                "search"
            ],
            "elements": "",
            "min": "",
            "max": 1,
            "return_format": "id"
        }
    ],
    "location": [
        [
            {
                "param": "block",
                "operator": "==",
                "value": "acf\/media-content-post"
            }
        ]
    ],
    "menu_order": 0,
    "position": "normal",
    "style": "default",
    "label_placement": "top",
    "instruction_placement": "label",
    "hide_on_screen": "",
    "active": true,
    "description": "",
    "show_in_rest": false,
    "modified": 1640600612
}